DjangoChineseDocs18/README.md
DjangoChineseDocs18/__init__.py
DjangoChineseDocs18/__main__.py
DjangoChineseDocs18/file.epub
DjangoChineseDocs18/index.html
DjangoChineseDocs18/css/__init__.py
DjangoChineseDocs18/css/annotations.css
DjangoChineseDocs18/css/main.css
DjangoChineseDocs18/css/normalize.css
DjangoChineseDocs18/css/popup.css
DjangoChineseDocs18/font/__init__.py
DjangoChineseDocs18/font/fontello.eot
DjangoChineseDocs18/font/fontello.svg
DjangoChineseDocs18/font/fontello.ttf
DjangoChineseDocs18/font/fontello.woff
DjangoChineseDocs18/img/__init__.py
DjangoChineseDocs18/img/annotator-glyph-sprite.png
DjangoChineseDocs18/img/annotator-icon-sprite.png
DjangoChineseDocs18/img/apple-touch-icon.png
DjangoChineseDocs18/img/cancelfullscreen.png
DjangoChineseDocs18/img/close.png
DjangoChineseDocs18/img/fullscreen.png
DjangoChineseDocs18/img/loader.gif
DjangoChineseDocs18/img/menu-icon.png
DjangoChineseDocs18/img/save.png
DjangoChineseDocs18/img/saved.png
DjangoChineseDocs18/img/settings-s.png
DjangoChineseDocs18/img/settings.png
DjangoChineseDocs18/img/star.png
DjangoChineseDocs18/js/__init__.py
DjangoChineseDocs18/js/epub.js
DjangoChineseDocs18/js/epub.min.js
DjangoChineseDocs18/js/epub.min.map
DjangoChineseDocs18/js/hooks.min.js
DjangoChineseDocs18/js/hooks.min.map
DjangoChineseDocs18/js/reader.js
DjangoChineseDocs18/js/reader.js.map
DjangoChineseDocs18/js/reader.min.js
DjangoChineseDocs18/js/reader.min.map
DjangoChineseDocs18/js/hooks/__init__.py
DjangoChineseDocs18/js/hooks/extensions/__init__.py
DjangoChineseDocs18/js/hooks/extensions/highlight.js
DjangoChineseDocs18/js/libs/__init__.py
DjangoChineseDocs18/js/libs/jquery.min.js
DjangoChineseDocs18/js/libs/localforage.min.js
DjangoChineseDocs18/js/libs/screenfull.js
DjangoChineseDocs18/js/libs/screenfull.min.js
DjangoChineseDocs18/js/libs/zip.min.js
DjangoChineseDocs18/js/plugins/__init__.py
DjangoChineseDocs18/js/plugins/hypothesis.js
DjangoChineseDocs18/js/plugins/search.js
django_chinese_docs_18-2024.3.1.0.dist-info/METADATA
django_chinese_docs_18-2024.3.1.0.dist-info/WHEEL
django_chinese_docs_18-2024.3.1.0.dist-info/entry_points.txt
django_chinese_docs_18-2024.3.1.0.dist-info/top_level.txt
django_chinese_docs_18-2024.3.1.0.dist-info/RECORD
